rchain_grpc/__init__.py
rchain_grpc/casper.py
rchain_grpc/cli.py
rchain_grpc/exceptions.py
rchain_grpc/generate.sh
rchain_grpc/rchain_grpc.py
rchain_grpc/repl.py
rchain_grpc/rho_types.py
rchain_grpc/utils.py
rchain_grpc/generated/CasperMessage_pb2.py
rchain_grpc/generated/CasperMessage_pb2_grpc.py
rchain_grpc/generated/RhoTypes_pb2.py
rchain_grpc/generated/RhoTypes_pb2_grpc.py
rchain_grpc/generated/__init__.py
rchain_grpc/generated/repl_pb2.py
rchain_grpc/generated/repl_pb2_grpc.py
rchain_grpc/generated/scalapb/__init__.py
rchain_grpc/generated/scalapb/scalapb_pb2.py
rchain_grpc/generated/scalapb/scalapb_pb2_grpc.py
rchain_grpc/proto/CasperMessage.proto
rchain_grpc/proto/RhoTypes.proto
rchain_grpc/proto/repl.proto
rchain_grpc/proto/scalapb/scalapb.proto
rchain_grpc-0.0.7.dist-info/METADATA
rchain_grpc-0.0.7.dist-info/RECORD
rchain_grpc-0.0.7.dist-info/WHEEL
rchain_grpc-0.0.7.dist-info/entry_points.txt
rchain_grpc-0.0.7.dist-info/top_level.txt
rchain_grpc-0.0.7.dist-info/zip-safe
