Metadata-Version: 2.1
Name: rchain-grpc
Version: 0.0.7
Summary: python client to rchain gRPC
Home-page: https://github.com/proof-media/rchain_grpc
Author: Mateusz Probachta
Author-email: mateusz@proofmedia.io
License: MIT license
Keywords: rchain_grpc
Platform: UNKNOWN
Classifier: Development Status :: 2 - Pre-Alpha
Classifier: Intended Audience :: Developers
Classifier: License :: OSI Approved :: MIT License
Classifier: Natural Language :: English
Classifier: Programming Language :: Python :: 3
Classifier: Programming Language :: Python :: 3.7
Classifier: Programming Language :: Python :: 3 :: Only
Requires-Dist: Click (>=6.0)
Requires-Dist: toolz
Requires-Dist: grpcio
Requires-Dist: googleapis-common-protos
